{
    "boot": "workspace",
    "engine": [
        "node"
    ],
    "packages": {
        "workspace": {
            "locator": {
                "location": "./"
            }
        },
        "github.com/pinf/docs-js/": {
            "locator": {
                "archive": "https://github.com/pinf/docs-js/zipball/master"
            }
        },
        "nodejs.org": {
            "provider": "nodejs.org"
        },
        "pinf.org/loader": {
            "provider": "pinf.org/loader"
        },
        "github.com/kriszyp/jsgi-node/": {
            "locator": {
                "archive": "https://github.com/kriszyp/jsgi-node/zipball/v0.2.4",
                "descriptor": {
                    "uid": "https://github.com/kriszyp/jsgi-node/",
                    "native": true
                }
            }
        },
        "github.com/senchalabs/connect/": {
            "locator": {
                "archive": "https://github.com/senchalabs/connect/zipball/master",
                "descriptor": {
                    "uid": "http://github.com/senchalabs/connect/",
                    "native": true,
                    "dependencies": [
                        {
                            "id": "registry.npmjs.org/qs/"
                        },
                        {
                            "id": "github.com/bentomas/node-mime/"
                        }
                    ]
                }
            }
        },
        "registry.npmjs.org/qs/": {
            "locator": {
                "archive": "http://registry.npmjs.org/qs/-/qs-0.0.6.tgz",
                "descriptor": {
                    "uid": "http://registry.npmjs.org/qs/",
                    "native": true
                }
            }
        },
        "github.com/bentomas/node-mime/": {
            "locator": {
                "archive": "https://github.com/bentomas/node-mime/zipball/master",
                "descriptor": {
                    "uid": "https://github.com/bentomas/node-mime/",
                    "native": true,
                    "directories": {
                        "lib": ""
                    }
                }
            }
        },
        "github.com/pinf/modules-js/": {
            "locator": {
                "archive": "https://github.com/pinf/modules-js/zipball/master"
            }
        },
        "github.com/kriskowal/q/": {
            "locator": {
                "archive": "https://github.com/kriskowal/q/zipball/v0.3.0"
            },
            "descriptor": {
                "uid": "https://github.com/kriskowal/q/",
                "dependencies": [
                    {
                        "id": "github.com/pinf/modules-js/"
                    }
                ]
            }
        },
        "github.com/cadorn/markdown-js/": {
            "locator": {
                "archive": "https://github.com/cadorn/markdown-js/zipball/master",
                "descriptor": {
                    "uid": "https://github.com/cadorn/markdown-js/"
                }
            }            
        },
        "alexgorbatchev.com/SyntaxHighlighter/": {
            "locator": {
                "archive": "https://bitbucket.org/alexg/syntaxhighlighter/get/3.0.83.zip",
                "resource": true
            },
            "descriptor": {
                "uid": "http://alexgorbatchev.com/SyntaxHighlighter/",
                "directories": {
                    "lib": "scripts"
                }
            }
        },
        "jqueryui.com/": {
            "locator": {
                "archive": "http://jqueryui.com/download/jquery-ui-1.8.13.custom.zip",
                "resource": true
            },
            "descriptor": {
                "uid": "http://jqueryui.com/",
                "directories": {
                    "lib": "js"
                }
            }
        }
    }
}